csmemo/__init__.py
csmemo/consistency_analysis.py
csmemo/csmbuilder.py
csmemo/io.py
csmemo/manipulate.py
csmemo/reachability.py
csmemo/cmds/__init__.py
csmemo/cmds/build_csm.py
csmemo/cmds/gpr_mapping.py
csmemo/cmds/run_insilico_experiment.py
csmemo/cmds/run_reachability_analysis.py
csmemo/cmds/trimm_model.py
csmemo/plots/common_plots.py
csmemo/plots/reachability_plots.py
csmemo-0.0.9.dist-info/LICENSE
csmemo-0.0.9.dist-info/METADATA
csmemo-0.0.9.dist-info/WHEEL
csmemo-0.0.9.dist-info/entry_points.txt
csmemo-0.0.9.dist-info/top_level.txt
csmemo-0.0.9.dist-info/RECORD
