Metadata-Version: 2.1
Name: csmemo
Version: 0.0.9
Summary: A Library implementing constraint-based methods for context-specific metabolic modeling
Author-email: Miguel Ponce de Leon <miguel.ponce@bsc.es>
License: BSD 3-Clause License
Project-URL: Homepage, https://github.com/bsc-life/csmemo
Project-URL: Bug Tracker, https://github.com/bsc-life/csmemo/issues
Classifier: Programming Language :: Python :: 3
Classifier: License :: OSI Approved :: MIT License
Classifier: Operating System :: OS Independent
Requires-Python: >=3.8
License-File: LICENSE
Requires-Dist: numpy
Requires-Dist: networkx
Requires-Dist: pandas
Requires-Dist: cobra >=0.25.0
Requires-Dist: pyfastcore
Requires-Dist: boolean.py
Requires-Dist: corda
